commodplot/__init__.py
commodplot/commodplot.py
commodplot/commodplottable.py
commodplot/commodplottrace.py
commodplot/commodplottransform.py
commodplot/commodplotutil.py
commodplot/jinjautils.py
commodplot/messaging.py
commodplot/templates/base.html
commodplot/templates/macros.html
commodplot/templates/styles.css
commodplot/templates/test_report.html
commodplot-3.4.0.dist-info/METADATA
commodplot-3.4.0.dist-info/WHEEL
commodplot-3.4.0.dist-info/top_level.txt
commodplot-3.4.0.dist-info/RECORD
